quart_rate_limiter-0.12.1.dist-info/METADATA
quart_rate_limiter-0.12.1.dist-info/WHEEL
quart_rate_limiter-0.12.1.dist-info/entry_points.txt
quart_rate_limiter-0.12.1.dist-info/licenses/LICENSE
quart_rate_limiter/__init__.py
quart_rate_limiter/py.typed
quart_rate_limiter/redis_store.py
quart_rate_limiter/store.py
quart_rate_limiter/valkey_store.py
quart_rate_limiter-0.12.1.dist-info/RECORD
